neuralnet/__init__.py
neuralnet/build_optimization.py
neuralnet/build_training.py
neuralnet/extras.py
neuralnet/init.py
neuralnet/layers.py
neuralnet/metrics.py
neuralnet/model.py
neuralnet/model_zoo.py
neuralnet/monitor.py
neuralnet/normalization.py
neuralnet/optimization.py
neuralnet/read_data.py
neuralnet/resizing.py
neuralnet/test.py
neuralnet/transforms.py
neuralnet/utils.py
neuralnet/version.py
neuralnet-0.2.0.dist-info/LICENSE.txt
neuralnet-0.2.0.dist-info/METADATA
neuralnet-0.2.0.dist-info/WHEEL
neuralnet-0.2.0.dist-info/top_level.txt
neuralnet-0.2.0.dist-info/RECORD
