Metadata-Version: 2.1
Name: neuralnet
Version: 0.2.0
Summary: A high-level library on top of Theano.
Home-page: https://github.com/justanhduc/neuralnet
Author: Duc Nguyen
Author-email: adnguyen@yonsei.ac.kr
License: UNKNOWN
Project-URL: Bug Reports, https://github.com/justanhduc/neuralnet/issues
Project-URL: Source, https://github.com/justanhduc/neuralnet/
Platform: Windows
Platform: Linux
Classifier: Development Status :: 3 - Alpha
Classifier: Intended Audience :: End Users/Desktop
Classifier: License :: OSI Approved :: Mozilla Public License 2.0 (MPL 2.0)
Classifier: Operating System :: Microsoft :: Windows :: Windows 10
Classifier: Programming Language :: Python :: 3 :: Only
Classifier: Programming Language :: Python :: 3.5
Requires-Dist: theano
Requires-Dist: matplotlib
Requires-Dist: scipy
Requires-Dist: numpy
Requires-Dist: tqdm
Requires-Dist: visdom
